django_general_purpose_forms/__init__.py
django_general_purpose_forms/admin.py
django_general_purpose_forms/apps.py
django_general_purpose_forms/forms.py
django_general_purpose_forms/migrations/0001_initial.py
django_general_purpose_forms/migrations/__init__.py
django_general_purpose_forms/models.py
django_general_purpose_forms/templates/django_general_purpose_forms/form.html
django_general_purpose_forms/urls.py
django_general_purpose_forms/views.py
django_general_purpose_forms-0.3.0.dist-info/METADATA
django_general_purpose_forms-0.3.0.dist-info/WHEEL
django_general_purpose_forms-0.3.0.dist-info/licenses/LICENSE
django_general_purpose_forms-0.3.0.dist-info/RECORD
