Metadata-Version: 2.4
Name: django_general_purpose_forms
Version: 0.3.0
Summary: Bind forms to arbitrary objects with ease!
License: GNU GPLv3
License-File: LICENSE
Author: Kapt dev team
Author-email: dev@kapt.mobi
Requires-Python: >=3.12
Classifier: License :: Other/Proprietary License
Classifier: Programming Language :: Python :: 3
Classifier: Programming Language :: Python :: 3.12
Classifier: Programming Language :: Python :: 3.13
Classifier: Programming Language :: Python :: 3.14
Requires-Dist: Django (>=3.2)
Project-URL: Repository, https://gitlab.com/kapt/open-source/django-generic-contact-form
